aiofix/__init__.py
aiofix/client.py
aiofix/engine_streams.py
aiofix/message.py
aiofix/msgtype.py
aiofix/py.typed
aiofix/server.py
aiofix/spec.py
aiofix/tags.py
aiofix/validator.py
aiofixproto-0.0.1.dist-info/METADATA
aiofixproto-0.0.1.dist-info/WHEEL
aiofixproto-0.0.1.dist-info/top_level.txt
aiofixproto-0.0.1.dist-info/RECORD
