Metadata-Version: 2.1
Name: aiofixproto
Version: 0.0.1
Summary: Speak FIX using asyncio
Author-email: Chris Shucksmith <chris@shucksmith.co.uk>
Project-URL: Homepage, https://github.com/TeaEngineering/aiofixproto
Project-URL: Issues, https://github.com/TeaEngineering/aiofixproto/issues
Classifier: Programming Language :: Python :: 3.9
Classifier: Programming Language :: Python :: 3.10
Classifier: Programming Language :: Python :: 3.11
Classifier: Programming Language :: Python :: 3.12
Classifier: License :: OSI Approved :: MIT License
Classifier: Operating System :: OS Independent
Requires-Python: >=3.9
